main.py
setup.py
bytepps.egg-info/PKG-INFO
bytepps.egg-info/SOURCES.txt
bytepps.egg-info/dependency_links.txt
bytepps.egg-info/requires.txt
bytepps.egg-info/top_level.txt